{"nm":"Frame 408","v":"5.9.6","fr":60,"ip":0,"op":311,"w":692,"h":417,"ddd":0,"markers":[],"assets":[{"nm":"[GROUP] Ellipse 1078 - Null / Ellipse 1078 / Rectangle 87 - Null / Rectangle 87 - Stroke / Vector - Null / Vector - Stroke","fr":60,"id":"ller2shzbv3boecvuza","layers":[{"ty":3,"ddd":0,"ind":7,"hd":false,"nm":"Group 390 - Null","ks":{"a":{"a":0,"k":[61.376,57.5406]},"o":{"a":0,"k":100},"p":{"a":0,"k":[417.2935,276.9292]},"r":{"a":0,"k":0},"s":{"a":0,"k":[100,100]},"sk":{"a":0,"k":0},"sa":{"a":0,"k":0}},"st":0,"ip":0,"op":312,"bm":0,"sr":1},{"ty":3,"ddd":0,"ind":8,"hd":false,"nm":"Ellipse 1078 - Null","parent":7,"ks":{"a":{"a":0,"k":[11.3661,0]},"o":{"a":0,"k":100},"p":{"a":1,"k":[{"t":0,"s":[249.3661,35.8086],"o":{"x":[0.5],"y":[0.35]},"i":{"x":[0.15],"y":[1]},"ti":[0,0],"to":[0,0]},{"t":72,"s":[6.366099999999999,35.8086],"o":{"x":[0.5],"y":[0.35]},"i":{"x":[0.15],"y":[1]},"ti":[0,0],"to":[0,0]},{"t":240,"s":[6.366099999999999,35.81],"o":{"x":[0.5],"y":[0.35]},"i":{"x":[0.15],"y":[1]},"ti":[0,0],"to":[0,0]},{"t":312,"s":[249.3661,35.81]}]},"r":{"a":0,"k":0},"s":{"a":0,"k":[100,100]},"sk":{"a":0,"k":0},"sa":{"a":0,"k":0}},"st":0,"ip":0,"op":312,"bm":0,"sr":1},{"ty":4,"ddd":0,"ind":9,"hd":false,"nm":"Ellipse 1078","parent":8,"ks":{"a":{"a":0,"k":[0,0]},"p":{"a":0,"k":[0,0]},"s":{"a":0,"k":[100,100]},"sk":{"a":0,"k":0},"sa":{"a":0,"k":0},"r":{"a":0,"k":0},"o":{"a":0,"k":100}},"st":0,"ip":0,"op":312,"bm":0,"sr":1,"shapes":[{"ty":"gr","nm":"Group","hd":false,"np":3,"it":[{"ty":"sh","nm":"Path","hd":false,"ks":{"a":0,"k":{"c":true,"v":[[22.7321,11.3661],[11.3661,22.7321],[0,11.3661],[11.3661,0],[22.7321,11.3661],[22.7321,11.3661]],"i":[[0,0],[6.2775,0],[0,6.2775],[-6.2775,0],[0,-6.2775],[0,0]],"o":[[0,6.2775],[-6.2775,0],[0,-6.2775],[6.2775,0],[0,0],[0,0]]}}},{"ty":"fl","o":{"a":0,"k":100},"c":{"a":0,"k":[0.6196078431372549,0.4666666666666667,0.9294117647058824,1]},"nm":"Fill","hd":false,"r":1},{"ty":"tr","a":{"a":0,"k":[0,0]},"p":{"a":0,"k":[0,0]},"s":{"a":0,"k":[100,100]},"sk":{"a":0,"k":0},"sa":{"a":0,"k":0},"r":{"a":0,"k":0},"o":{"a":0,"k":100}}]}]},{"ty":3,"ddd":0,"ind":10,"hd":false,"nm":"Rectangle 87 - Null","parent":7,"ks":{"a":{"a":0,"k":[0,0]},"o":{"a":1,"k":[{"t":0,"s":[0],"o":{"x":[0.5],"y":[0.35]},"i":{"x":[0.15],"y":[1]}},{"t":150,"s":[100],"o":{"x":[0.5],"y":[0.35]},"i":{"x":[0.15],"y":[1]}},{"t":300,"s":[0]}]},"p":{"a":0,"k":[100.0198,0]},"r":{"a":0,"k":0},"s":{"a":0,"k":[100,100]},"sk":{"a":0,"k":0},"sa":{"a":0,"k":0}},"st":0,"ip":0,"op":312,"bm":0,"sr":1},{"ddd":0,"ind":11,"hd":false,"nm":"Rectangle 87 - Stroke","parent":10,"ks":{"a":{"a":0,"k":[0,0]},"p":{"a":0,"k":[0,0]},"s":{"a":0,"k":[100,100]},"sk":{"a":0,"k":0},"sa":{"a":0,"k":0},"r":{"a":0,"k":0},"o":{"a":1,"k":[{"t":0,"s":[0],"o":{"x":[0.5],"y":[0.35]},"i":{"x":[0.15],"y":[1]}},{"t":150,"s":[100],"o":{"x":[0.5],"y":[0.35]},"i":{"x":[0.15],"y":[1]}},{"t":300,"s":[0]}]}},"st":0,"ip":0,"op":312,"bm":0,"sr":1,"ty":4,"shapes":[{"ty":"gr","nm":"Group","hd":false,"np":5,"it":[{"ty":"sh","nm":"Path","hd":false,"ks":{"a":0,"k":{"c":false,"v":[[0,57.5406],[0,23.917]],"i":[[0,0],[0,0]],"o":[[0,0],[0,0]]}}},{"ty":"sh","nm":"Path","hd":false,"ks":{"a":0,"k":{"c":false,"v":[[22.7321,5.9792],[0,23.9169]],"i":[[0,0],[0,-9.9067]],"o":[[-12.55458,0],[0,0]]}}},{"ty":"sh","nm":"Path","hd":false,"ks":{"a":0,"k":{"c":false,"v":[[0,23.917],[0,0]],"i":[[0,0],[0,0]],"o":[[0,0],[0,0]]}}},{"ty":"st","o":{"a":0,"k":100},"w":{"a":0,"k":8.8655},"c":{"a":0,"k":[1,1,1,1]},"ml":4,"lc":1,"lj":1,"nm":"Stroke","hd":false},{"ty":"tr","a":{"a":0,"k":[0,0]},"p":{"a":0,"k":[0,0]},"s":{"a":0,"k":[100,100]},"sk":{"a":0,"k":0},"sa":{"a":0,"k":0},"r":{"a":0,"k":0},"o":{"a":0,"k":100}}]},{"ty":"tm","s":{"a":0,"k":0},"e":{"a":1,"k":[{"t":72,"s":[0],"o":{"x":[0.5],"y":[0.35]},"i":{"x":[0.15],"y":[1]}},{"t":150,"s":[100],"o":{"x":[0.5],"y":[0.35]},"i":{"x":[0.15],"y":[1]}},{"t":300,"s":[0]}]},"o":{"a":0,"k":0},"m":1},{"ty":"gr","nm":"Group","hd":false,"np":3,"it":[{"ty":"rc","nm":"Rectangle","hd":false,"p":{"a":0,"k":[15.7988,33.20305]},"s":{"a":0,"k":[63.1952,132.8122]},"r":{"a":0,"k":0}},{"ty":"fl","o":{"a":0,"k":0},"c":{"a":0,"k":[0,1,0,1]},"nm":"Fill","hd":false,"r":1},{"ty":"tr","a":{"a":0,"k":[0,0]},"p":{"a":0,"k":[0,0]},"s":{"a":0,"k":[100,100]},"sk":{"a":0,"k":0},"sa":{"a":0,"k":0},"r":{"a":0,"k":0},"o":{"a":0,"k":100}}]}]},{"ty":3,"ddd":0,"ind":12,"hd":false,"nm":"Vector - Null","parent":7,"ks":{"a":{"a":0,"k":[0,0]},"o":{"a":1,"k":[{"t":72,"s":[0],"o":{"x":[0.5],"y":[0.35]},"i":{"x":[0.15],"y":[1]}},{"t":150,"s":[100],"o":{"x":[0.5],"y":[0.35]},"i":{"x":[0.15],"y":[1]}},{"t":300,"s":[0]}]},"p":{"a":0,"k":[38.86609999999996,1.448399999999992]},"r":{"a":0,"k":0},"s":{"a":0,"k":[100,100]},"sk":{"a":0,"k":0},"sa":{"a":0,"k":0}},"st":0,"ip":0,"op":312,"bm":0,"sr":1},{"ddd":0,"ind":13,"hd":false,"nm":"Vector - Stroke","parent":12,"ks":{"a":{"a":0,"k":[0,0]},"p":{"a":0,"k":[0,0]},"s":{"a":0,"k":[100,100]},"sk":{"a":0,"k":0},"sa":{"a":0,"k":0},"r":{"a":0,"k":0},"o":{"a":1,"k":[{"t":72,"s":[0],"o":{"x":[0.5],"y":[0.35]},"i":{"x":[0.15],"y":[1]}},{"t":150,"s":[100],"o":{"x":[0.5],"y":[0.35]},"i":{"x":[0.15],"y":[1]}},{"t":300,"s":[0]}]}},"st":0,"ip":0,"op":312,"bm":0,"sr":1,"ty":4,"shapes":[{"ty":"gr","nm":"Group","hd":false,"np":4,"it":[{"ty":"sh","nm":"Path","hd":false,"ks":{"a":0,"k":{"c":false,"v":[[45.7805,22.8903],[22.8903,0],[0,22.8903],[0,29.235],[22.8903,52.1253],[39.5101,44.9751]],"i":[[0,0],[12.6419,0],[0,-12.6419],[0,0],[-12.6419,0],[-4.1718,4.4035]],"o":[[0,-12.64193],[-12.64193,0],[0,0],[0,12.641930000000002],[6.544740000000001,0],[0,0]]}}},{"ty":"sh","nm":"Path","hd":false,"ks":{"a":0,"k":{"c":false,"v":[[3.3754,26.0763],[49.7874,26.0763]],"i":[[0,0],[0,0]],"o":[[0,0],[0,0]]}}},{"ty":"st","o":{"a":0,"k":100},"w":{"a":0,"k":8.0024},"c":{"a":0,"k":[1,1,1,1]},"ml":4,"lc":1,"lj":1,"nm":"Stroke","hd":false},{"ty":"tr","a":{"a":0,"k":[0,0]},"p":{"a":0,"k":[0,0]},"s":{"a":0,"k":[100,100]},"sk":{"a":0,"k":0},"sa":{"a":0,"k":0},"r":{"a":0,"k":0},"o":{"a":0,"k":100}}]},{"ty":"tm","s":{"a":0,"k":0},"e":{"a":1,"k":[{"t":71.39999999999999,"s":[100],"o":{"x":[0.5],"y":[0.35]},"i":{"x":[0.15],"y":[1]}},{"t":72,"s":[0],"o":{"x":[0.5],"y":[0.35]},"i":{"x":[0.15],"y":[1]}},{"t":150,"s":[100],"o":{"x":[0.5],"y":[0.35]},"i":{"x":[0.15],"y":[1]}},{"t":300,"s":[0]}]},"o":{"a":0,"k":0},"m":1},{"ty":"gr","nm":"Group","hd":false,"np":3,"it":[{"ty":"rc","nm":"Rectangle","hd":false,"p":{"a":0,"k":[28.89495,30.0638]},"s":{"a":0,"k":[115.5798,120.2552]},"r":{"a":0,"k":0}},{"ty":"fl","o":{"a":0,"k":0},"c":{"a":0,"k":[0,1,0,1]},"nm":"Fill","hd":false,"r":1},{"ty":"tr","a":{"a":0,"k":[0,0]},"p":{"a":0,"k":[0,0]},"s":{"a":0,"k":[100,100]},"sk":{"a":0,"k":0},"sa":{"a":0,"k":0},"r":{"a":0,"k":0},"o":{"a":0,"k":100}}]}]}]},{"nm":"Frame 408","fr":60,"id":"ller2shrd6xoan45i0i","layers":[{"ty":3,"ddd":0,"ind":14,"hd":false,"nm":"Frame 408 - Null","ks":{"a":{"a":0,"k":[0,0]},"o":{"a":0,"k":100},"p":{"a":0,"k":[0,0]},"r":{"a":0,"k":0},"s":{"a":0,"k":[100,100]},"sk":{"a":0,"k":0},"sa":{"a":0,"k":0}},"st":0,"ip":0,"op":312,"bm":0,"sr":1},{"ty":3,"ddd":0,"ind":15,"hd":false,"nm":"Rectangle 1027 - Null","parent":14,"ks":{"a":{"a":0,"k":[0,159.1245]},"o":{"a":0,"k":100},"p":{"a":0,"k":[284.4663,276.9286]},"r":{"a":0,"k":0},"s":{"a":0,"k":[100,100]},"sk":{"a":0,"k":0},"sa":{"a":0,"k":0}},"st":0,"ip":0,"op":312,"bm":0,"sr":1},{"ddd":0,"ind":16,"hd":false,"nm":"Rectangle 1027 - Stroke","parent":15,"ks":{"a":{"a":0,"k":[0,0]},"p":{"a":0,"k":[0,0]},"s":{"a":0,"k":[100,100]},"sk":{"a":0,"k":0},"sa":{"a":0,"k":0},"r":{"a":0,"k":0},"o":{"a":0,"k":100}},"st":0,"ip":0,"op":312,"bm":0,"sr":1,"ty":4,"shapes":[{"ty":"gr","nm":"Group","hd":false,"np":3,"it":[{"ty":"sh","nm":"Path","hd":false,"ks":{"a":1,"k":[{"t":16.200000000000003,"s":[{"c":true,"v":[[28.415,102.2945],[130.7095,102.2945],[159.1245,130.7095],[159.1245,130.7095],[130.7095,159.1245],[28.415,159.1245],[0,130.7095],[0,130.7095],[28.415,102.2945],[28.415,102.2945]],"i":[[0,0],[0,0],[0,-15.6932],[0,0],[15.6932,0],[0,0],[0,15.6932],[0,0],[-15.6932,0],[0,0]],"o":[[0,0],[15.69317000000001,0],[0,0],[0,15.69317000000001],[0,0],[-15.69317,0],[0,0],[0,-15.693169999999995],[0,0],[0,0]]}],"o":{"x":[0.5],"y":[0.35]},"i":{"x":[0.15],"y":[1]}},{"t":72,"s":[{"c":true,"v":[[28.415,0],[28.415,0],[56.83,28.415],[56.83,130.7095],[28.415,159.1245],[28.415,159.1245],[0,130.7095],[0,28.415],[28.415,0],[28.415,0]],"i":[[0,0],[0,0],[0,-15.6932],[0,0],[15.6932,0],[0,0],[0,15.6932],[0,0],[-15.6932,0],[0,0]],"o":[[0,0],[15.693170000000002,0],[0,0],[0,15.69317000000001],[0,0],[-15.69317,0],[0,0],[0,-15.69317],[0,0],[0,0]]}],"o":{"x":[0.5],"y":[0.35]},"i":{"x":[0.15],"y":[1]}},{"t":240,"s":[{"c":true,"v":[[28.415,0],[28.415,0],[56.83,28.415],[56.83,130.7095],[28.415,159.1245],[28.415,159.1245],[0,130.7095],[0,28.415],[28.415,0],[28.415,0]],"i":[[0,0],[0,0],[0,-15.6932],[0,0],[15.6932,0],[0,0],[0,15.6932],[0,0],[-15.6932,0],[0,0]],"o":[[0,0],[15.693170000000002,0],[0,0],[0,15.69317000000001],[0,0],[-15.69317,0],[0,0],[0,-15.69317],[0,0],[0,0]]}],"o":{"x":[0.5],"y":[0.35]},"i":{"x":[0.15],"y":[1]}},{"t":312,"s":[{"c":true,"v":[[28.415,102.2945],[130.705,102.2945],[159.12,130.7095],[159.12,130.7095],[130.705,159.1245],[28.415,159.1245],[0,130.7095],[0,130.7095],[28.415,102.2945],[28.415,102.2945]],"i":[[0,0],[0,0],[0,-15.6932],[0,0],[15.6932,0],[0,0],[0,15.6932],[0,0],[-15.6932,0],[0,0]],"o":[[0,0],[15.69317000000001,0],[0,0],[0,15.69317000000001],[0,0],[-15.69317,0],[0,0],[0,-15.693169999999995],[0,0],[0,0]]}]}]}},{"ty":"st","o":{"a":0,"k":100},"w":{"a":0,"k":18.1856},"c":{"a":0,"k":[1,1,1,1]},"ml":4,"lc":1,"lj":1,"nm":"Stroke","hd":false},{"ty":"tr","a":{"a":0,"k":[0,0]},"p":{"a":0,"k":[0,0]},"s":{"a":0,"k":[100,100]},"sk":{"a":0,"k":0},"sa":{"a":0,"k":0},"r":{"a":0,"k":0},"o":{"a":0,"k":100}}]},{"ty":"gr","nm":"Group","hd":false,"np":3,"it":[{"ty":"rc","nm":"Rectangle","hd":false,"p":{"a":0,"k":[32.9615,84.10865000000001]},"s":{"a":0,"k":[131.846,336.43460000000005]},"r":{"a":0,"k":0}},{"ty":"fl","o":{"a":0,"k":0},"c":{"a":0,"k":[0,1,0,1]},"nm":"Fill","hd":false,"r":1},{"ty":"tr","a":{"a":0,"k":[0,0]},"p":{"a":0,"k":[0,0]},"s":{"a":0,"k":[100,100]},"sk":{"a":0,"k":0},"sa":{"a":0,"k":0},"r":{"a":0,"k":0},"o":{"a":0,"k":100}}]}],"hasMask":true,"masksProperties":[{"nm":"Mask","pt":{"a":1,"k":[{"t":16.200000000000003,"s":[{"c":true,"v":[[28.415,102.2945],[130.7095,102.2945],[159.1245,130.7095],[159.1245,130.7095],[130.7095,159.1245],[28.415,159.1245],[0,130.7095],[0,130.7095],[28.415,102.2945],[28.415,102.2945]],"i":[[0,0],[0,0],[0,-15.6932],[0,0],[15.6932,0],[0,0],[0,15.6932],[0,0],[-15.6932,0],[0,0]],"o":[[0,0],[15.69317000000001,0],[0,0],[0,15.69317000000001],[0,0],[-15.69317,0],[0,0],[0,-15.693169999999995],[0,0],[0,0]]}],"o":{"x":[0.5],"y":[0.35]},"i":{"x":[0.15],"y":[1]}},{"t":72,"s":[{"c":true,"v":[[28.415,0],[28.415,0],[56.83,28.415],[56.83,130.7095],[28.415,159.1245],[28.415,159.1245],[0,130.7095],[0,28.415],[28.415,0],[28.415,0]],"i":[[0,0],[0,0],[0,-15.6932],[0,0],[15.6932,0],[0,0],[0,15.6932],[0,0],[-15.6932,0],[0,0]],"o":[[0,0],[15.693170000000002,0],[0,0],[0,15.69317000000001],[0,0],[-15.69317,0],[0,0],[0,-15.69317],[0,0],[0,0]]}],"o":{"x":[0.5],"y":[0.35]},"i":{"x":[0.15],"y":[1]}},{"t":240,"s":[{"c":true,"v":[[28.415,0],[28.415,0],[56.83,28.415],[56.83,130.7095],[28.415,159.1245],[28.415,159.1245],[0,130.7095],[0,28.415],[28.415,0],[28.415,0]],"i":[[0,0],[0,0],[0,-15.6932],[0,0],[15.6932,0],[0,0],[0,15.6932],[0,0],[-15.6932,0],[0,0]],"o":[[0,0],[15.693170000000002,0],[0,0],[0,15.69317000000001],[0,0],[-15.69317,0],[0,0],[0,-15.69317],[0,0],[0,0]]}],"o":{"x":[0.5],"y":[0.35]},"i":{"x":[0.15],"y":[1]}},{"t":312,"s":[{"c":true,"v":[[28.415,102.2945],[130.705,102.2945],[159.12,130.7095],[159.12,130.7095],[130.705,159.1245],[28.415,159.1245],[0,130.7095],[0,130.7095],[28.415,102.2945],[28.415,102.2945]],"i":[[0,0],[0,0],[0,-15.6932],[0,0],[15.6932,0],[0,0],[0,15.6932],[0,0],[-15.6932,0],[0,0]],"o":[[0,0],[15.69317000000001,0],[0,0],[0,15.69317000000001],[0,0],[-15.69317,0],[0,0],[0,-15.693169999999995],[0,0],[0,0]]}]}]},"o":{"a":0,"k":100},"mode":"a","x":{"a":0,"k":0}}]},{"ty":4,"ddd":0,"ind":17,"hd":false,"nm":"Rectangle 1027","parent":15,"ks":{"a":{"a":0,"k":[0,0]},"p":{"a":0,"k":[0,0]},"s":{"a":0,"k":[100,100]},"sk":{"a":0,"k":0},"sa":{"a":0,"k":0},"r":{"a":0,"k":0},"o":{"a":0,"k":100}},"st":0,"ip":0,"op":312,"bm":0,"sr":1,"shapes":[{"ty":"gr","nm":"Group","hd":false,"np":3,"it":[{"ty":"sh","nm":"Path","hd":false,"ks":{"a":1,"k":[{"t":16.200000000000003,"s":[{"c":true,"v":[[28.415,102.2945],[130.7095,102.2945],[159.1245,130.7095],[159.1245,130.7095],[130.7095,159.1245],[28.415,159.1245],[0,130.7095],[0,130.7095],[28.415,102.2945],[28.415,102.2945]],"i":[[0,0],[0,0],[0,-15.6932],[0,0],[15.6932,0],[0,0],[0,15.6932],[0,0],[-15.6932,0],[0,0]],"o":[[0,0],[15.69317000000001,0],[0,0],[0,15.69317000000001],[0,0],[-15.69317,0],[0,0],[0,-15.693169999999995],[0,0],[0,0]]}],"o":{"x":[0.5],"y":[0.35]},"i":{"x":[0.15],"y":[1]}},{"t":72,"s":[{"c":true,"v":[[28.415,0],[28.415,0],[56.83,28.415],[56.83,130.7095],[28.415,159.1245],[28.415,159.1245],[0,130.7095],[0,28.415],[28.415,0],[28.415,0]],"i":[[0,0],[0,0],[0,-15.6932],[0,0],[15.6932,0],[0,0],[0,15.6932],[0,0],[-15.6932,0],[0,0]],"o":[[0,0],[15.693170000000002,0],[0,0],[0,15.69317000000001],[0,0],[-15.69317,0],[0,0],[0,-15.69317],[0,0],[0,0]]}],"o":{"x":[0.5],"y":[0.35]},"i":{"x":[0.15],"y":[1]}},{"t":240,"s":[{"c":true,"v":[[28.415,0],[28.415,0],[56.83,28.415],[56.83,130.7095],[28.415,159.1245],[28.415,159.1245],[0,130.7095],[0,28.415],[28.415,0],[28.415,0]],"i":[[0,0],[0,0],[0,-15.6932],[0,0],[15.6932,0],[0,0],[0,15.6932],[0,0],[-15.6932,0],[0,0]],"o":[[0,0],[15.693170000000002,0],[0,0],[0,15.69317000000001],[0,0],[-15.69317,0],[0,0],[0,-15.69317],[0,0],[0,0]]}],"o":{"x":[0.5],"y":[0.35]},"i":{"x":[0.15],"y":[1]}},{"t":312,"s":[{"c":true,"v":[[28.415,102.2945],[130.705,102.2945],[159.12,130.7095],[159.12,130.7095],[130.705,159.1245],[28.415,159.1245],[0,130.7095],[0,130.7095],[28.415,102.2945],[28.415,102.2945]],"i":[[0,0],[0,0],[0,-15.6932],[0,0],[15.6932,0],[0,0],[0,15.6932],[0,0],[-15.6932,0],[0,0]],"o":[[0,0],[15.69317000000001,0],[0,0],[0,15.69317000000001],[0,0],[-15.69317,0],[0,0],[0,-15.693169999999995],[0,0],[0,0]]}]}]}},{"ty":"fl","o":{"a":0,"k":100},"c":{"a":0,"k":[0.8509803921568627,0.8509803921568627,0.8509803921568627,1]},"nm":"Fill","hd":false,"r":1},{"ty":"tr","a":{"a":0,"k":[0,0]},"p":{"a":0,"k":[0,0]},"s":{"a":0,"k":[100,100]},"sk":{"a":0,"k":0},"sa":{"a":0,"k":0},"r":{"a":0,"k":0},"o":{"a":0,"k":100}}]}]},{"ty":3,"ddd":0,"ind":18,"hd":false,"nm":"Rectangle 1026 - Null","parent":14,"ks":{"a":{"a":0,"k":[0,0]},"o":{"a":1,"k":[{"t":0,"s":[0],"o":{"x":[0.5],"y":[0.35]},"i":{"x":[0.15],"y":[1]}},{"t":150,"s":[100],"o":{"x":[0.5],"y":[0.35]},"i":{"x":[0.15],"y":[1]}},{"t":300,"s":[0]}]},"p":{"a":0,"k":[216.3306,117.8041]},"r":{"a":0,"k":0},"s":{"a":0,"k":[100,100]},"sk":{"a":0,"k":0},"sa":{"a":0,"k":0}},"st":0,"ip":0,"op":312,"bm":0,"sr":1},{"ddd":0,"ind":19,"hd":false,"nm":"Rectangle 1026 - Stroke","parent":18,"ks":{"a":{"a":0,"k":[0,0]},"p":{"a":0,"k":[0,0]},"s":{"a":0,"k":[100,100]},"sk":{"a":0,"k":0},"sa":{"a":0,"k":0},"r":{"a":0,"k":0},"o":{"a":1,"k":[{"t":0,"s":[0],"o":{"x":[0.5],"y":[0.35]},"i":{"x":[0.15],"y":[1]}},{"t":150,"s":[100],"o":{"x":[0.5],"y":[0.35]},"i":{"x":[0.15],"y":[1]}},{"t":300,"s":[0]}]}},"st":0,"ip":0,"op":312,"bm":0,"sr":1,"ty":4,"shapes":[{"ty":"gr","nm":"Group","hd":false,"np":3,"it":[{"ty":"sh","nm":"Path","hd":false,"ks":{"a":0,"k":{"c":true,"v":[[0,0],[28.4151,0],[56.8302,28.4151],[56.8302,130.7094],[28.4151,159.1245],[0,159.1245],[0,159.1245],[0,0]],"i":[[0,0],[0,0],[0,-15.6932],[0,0],[15.6932,0],[0,0],[0,0],[0,0]],"o":[[0,0],[15.693229999999996,0],[0,0],[0,15.69323],[0,0],[0,0],[0,0],[0,0]]}}},{"ty":"st","o":{"a":0,"k":100},"w":{"a":0,"k":18.1856},"c":{"a":0,"k":[1,1,1,1]},"ml":4,"lc":1,"lj":1,"nm":"Stroke","hd":false},{"ty":"tr","a":{"a":0,"k":[0,0]},"p":{"a":0,"k":[0,0]},"s":{"a":0,"k":[100,100]},"sk":{"a":0,"k":0},"sa":{"a":0,"k":0},"r":{"a":0,"k":0},"o":{"a":0,"k":100}}]},{"ty":"tm","s":{"a":0,"k":0},"e":{"a":1,"k":[{"t":72,"s":[0],"o":{"x":[0.5],"y":[0.35]},"i":{"x":[0.15],"y":[1]}},{"t":150,"s":[100],"o":{"x":[0.5],"y":[0.35]},"i":{"x":[0.15],"y":[1]}},{"t":300,"s":[0]}]},"o":{"a":0,"k":0},"m":1},{"ty":"gr","nm":"Group","hd":false,"np":3,"it":[{"ty":"rc","nm":"Rectangle","hd":false,"p":{"a":0,"k":[32.9615,84.10865000000001]},"s":{"a":0,"k":[131.846,336.43460000000005]},"r":{"a":0,"k":0}},{"ty":"fl","o":{"a":0,"k":0},"c":{"a":0,"k":[0,1,0,1]},"nm":"Fill","hd":false,"r":1},{"ty":"tr","a":{"a":0,"k":[0,0]},"p":{"a":0,"k":[0,0]},"s":{"a":0,"k":[100,100]},"sk":{"a":0,"k":0},"sa":{"a":0,"k":0},"r":{"a":0,"k":0},"o":{"a":0,"k":100}}]}],"hasMask":true,"masksProperties":[{"nm":"Mask","pt":{"a":0,"k":{"c":true,"v":[[0,0],[28.4151,0],[56.8302,28.4151],[56.8302,130.7094],[28.4151,159.1245],[0,159.1245],[0,159.1245],[0,0]],"i":[[0,0],[0,0],[0,-15.6932],[0,0],[15.6932,0],[0,0],[0,0],[0,0]],"o":[[0,0],[15.693229999999996,0],[0,0],[0,15.69323],[0,0],[0,0],[0,0],[0,0]]}},"o":{"a":0,"k":100},"mode":"a","x":{"a":0,"k":0}}]},{"ty":4,"ddd":0,"ind":20,"hd":false,"nm":"Rectangle 1026","parent":18,"ks":{"a":{"a":0,"k":[0,0]},"p":{"a":0,"k":[0,0]},"s":{"a":0,"k":[100,100]},"sk":{"a":0,"k":0},"sa":{"a":0,"k":0},"r":{"a":0,"k":0},"o":{"a":1,"k":[{"t":0,"s":[0],"o":{"x":[0.5],"y":[0.35]},"i":{"x":[0.15],"y":[1]}},{"t":150,"s":[100],"o":{"x":[0.5],"y":[0.35]},"i":{"x":[0.15],"y":[1]}},{"t":300,"s":[0]}]}},"st":0,"ip":0,"op":312,"bm":0,"sr":1,"shapes":[{"ty":"gr","nm":"Group","hd":false,"np":3,"it":[{"ty":"sh","nm":"Path","hd":false,"ks":{"a":0,"k":{"c":true,"v":[[0,0],[28.4151,0],[56.8302,28.4151],[56.8302,130.7094],[28.4151,159.1245],[0,159.1245],[0,159.1245],[0,0]],"i":[[0,0],[0,0],[0,-15.6932],[0,0],[15.6932,0],[0,0],[0,0],[0,0]],"o":[[0,0],[15.693229999999996,0],[0,0],[0,15.69323],[0,0],[0,0],[0,0],[0,0]]}}},{"ty":"fl","o":{"a":0,"k":100},"c":{"a":0,"k":[0.8509803921568627,0.8509803921568627,0.8509803921568627,1]},"nm":"Fill","hd":false,"r":1},{"ty":"tr","a":{"a":0,"k":[0,0]},"p":{"a":0,"k":[0,0]},"s":{"a":0,"k":[100,100]},"sk":{"a":0,"k":0},"sa":{"a":0,"k":0},"r":{"a":0,"k":0},"o":{"a":0,"k":100}}]}]},{"ddd":0,"ind":21,"ty":0,"nm":"Group 390","refId":"ller2shzbv3boecvuza","sr":1,"ks":{"a":{"a":0,"k":[0,0]},"p":{"a":0,"k":[0,0]},"s":{"a":0,"k":[100,100]},"sk":{"a":0,"k":0},"sa":{"a":0,"k":0},"r":{"a":0,"k":0},"o":{"a":0,"k":100}},"ao":0,"w":692,"h":417,"ip":0,"op":312,"st":0,"hd":false,"bm":0}]}],"layers":[{"ty":3,"ddd":0,"ind":14,"hd":false,"nm":"Frame 408 - Null","ks":{"a":{"a":0,"k":[0,0]},"o":{"a":0,"k":100},"p":{"a":0,"k":[0,0]},"r":{"a":0,"k":0},"s":{"a":0,"k":[100,100]},"sk":{"a":0,"k":0},"sa":{"a":0,"k":0}},"st":0,"ip":0,"op":312,"bm":0,"sr":1},{"ddd":0,"ind":2,"ty":0,"nm":"Frame 408","refId":"ller2shrd6xoan45i0i","sr":1,"ks":{"a":{"a":0,"k":[0,0]},"p":{"a":0,"k":[0,0]},"s":{"a":0,"k":[100,100]},"sk":{"a":0,"k":0},"sa":{"a":0,"k":0},"r":{"a":0,"k":0},"o":{"a":0,"k":100}},"ao":0,"w":692,"h":417,"ip":0,"op":312,"st":0,"hd":false,"bm":0}],"meta":{"a":"","d":"","tc":"","g":"Aninix"}}